{
  "total_responses": 82,
  "demographics": {
    "colleges": {
      "科技學院": 13,
      "管理學院": 27,
      "人文學院": 26,
      "教育學院": 12,
      "智慧農學院": 2,
      "護理學院": 2
    },
    "identities": {
      "大一": 44,
      "大四予以上": 7,
      "大三": 10,
      "大二": 15,
      "畢業校友(具在校學號)": 3,
      "博士班": 1,
      "教員": 1,
      "碩士班(含在職班有學號者)": 1
    },
    "familiarity": {
      "普通，只熟悉自己學院和常去的幾個地方": 34,
      "熟悉，知道大部分主要建築和路線": 32,
      "完全不熟，我是新生/第一次來": 5,
      "非常熟悉，幾乎每個角落都知道": 4,
      "不太熟，經常需要找路": 7
    }
  },
  "wayfinding": {
    "使用 Google Maps 或其他手機地圖 App": 37,
    "詢問同學、朋友或路人": 49,
    "事先上網查詢建築物外觀或位置資訊": 35,
    "憑藉大概方向感自己摸索": 36,
    "查看校園內的實體地圖或指示牌": 50,
    "Line暨大群、dcard": 1
  },
  "problems": {
    "problems": {
      "1.建築物名稱標示不清或錯誤（例如只標示「綜合教學大樓」，而非「A、B棟」）": 45,
      "2.無法導航至「特定教室編號」": 48,
      "4.導航到室外就結束，無法指引進入建築物後的方向": 31,
      "3.規劃的步行路線很繞路，或不是最佳捷徑": 19,
      "5.定位不準確，位置飄移": 19,
      "6.很少使用或沒遇過問題": 17,
      "有射箭場的的街景圖，但並不知道要如何過去（去的過程沒有街景圖）": 1,
      "左轉的路是滾下山": 1
    },
    "most_annoying": {
      "1": 14,
      "2": 28,
      "6": 12,
      "5": 8,
      "4": 12,
      "3": 3,
      "7": 5
    }
  },
  "late_experience": {
    "幾乎沒有": 31,
    "偶爾發生": 30,
    "從未發生": 21
  },
  "desired_features": {
    "features": {
      "精準的室內定位：能指引到特定教室門口": 49,
      "地標搜尋功能：可用教室編號（如 A100）、建築物名稱或辦公室名稱搜尋": 60,
      "預估步行時間": 35,
      "周邊設施標示：如廁所、飲水機、影印機、販賣機等": 27,
      "無障礙路線：提供避開階梯、有電梯的路線": 8,
      "錯誤回報機制：讓使用者可以回報錯誤的資訊": 20,
      "最佳化路徑：提供最快、最短的步行捷徑": 45,
      "提供的路徑是人走的，而不是機車道汽車道。還有出校園提示": 1,
      "提供教室鑰匙要到哪間辦公室借，或是開門同學可以填寫教室門是否開著": 1
    },
    "helpfulness": {
      "5": 25,
      "3": 10,
      "4": 36,
      "2": 8,
      "1": 3
    },
    "report_willingness": {
      "1": 26,
      "5": 5,
      "2": 27,
      "4": 9,
      "3": 15
    },
    "nps": {
      "scores": [
        10,
        10,
        10,
        8,
        10,
        7,
        10,
        5,
        9,
        7,
        8,
        8,
        9,
        8,
        10,
        10,
        5,
        10,
        8,
        10,
        10,
        10,
        10,
        10,
        10,
        10,
        7,
        10,
        8,
        8,
        10,
        8,
        10,
        10,
        10,
        10,
        9,
        8,
        10,
        8,
        7,
        10,
        9,
        8,
        7,
        10,
        10,
        10,
        8,
        7,
        8,
        7,
        10,
        8,
        10,
        8,
        9,
        10,
        9,
        8,
        10,
        8,
        10,
        10,
        10,
        10,
        8,
        10,
        10,
        10,
        10,
        10,
        8,
        10,
        7,
        6,
        7,
        7,
        10,
        8,
        6,
        7
      ],
      "avg": 8.817073170731707,
      "promoters": 47,
      "passives": 31,
      "detractors": 4,
      "nps_score": 52.4390243902439
    }
  },
  "website_usage": {
    "否": 32,
    "是": 50
  },
  "qualitative_counts": {
    "lost_experiences": 10,
    "urgent_needs": 82,
    "general_suggestions": 17,
    "website_suggestions": 20,
    "contact_count": 9
  }
}